{
  "user": {
    "name": null,
    "preferences": []
  },
  "facts": [],
  "session_count": 10,
  "last_session": "2026-04-10T08:21:16.190479",
  "task_history": [
    {
      "task": "test",
      "ts": "2026-04-10T03:01:33.330249"
    },
    {
      "task": "Thank you.",
      "ts": "2026-04-10T06:13:49.388915"
    },
    {
      "task": "Good.",
      "ts": "2026-04-10T06:35:48.022109"
    },
    {
      "task": "Okay, I'll leave right here.",
      "ts": "2026-04-10T07:00:41.632823"
    },
    {
      "task": "Yeah.",
      "ts": "2026-04-10T07:05:57.373086"
    },
    {
      "task": "ଯବାନ କରେ",
      "ts": "2026-04-10T08:01:40.996269"
    },
    {
      "task": "É... É isso aí pessoal. Obrigado pela visita, obrigada pelo apoio de sempre aqui no canal do Teto Baixista. Nos vemos em",
      "ts": "2026-04-10T08:12:05.647731"
    },
    {
      "task": "(microfone captado a 2 metros da fonte)",
      "ts": "2026-04-10T08:12:31.964623"
    },
    {
      "task": ". . 0:02.5 seconds, : I'm gonna show you how to make a very special drink that's good for the body and tastes really nic",
      "ts": "2026-04-10T08:12:59.673956"
    },
    {
      "task": ". Ahem... 8 seconds of intro music? Ugh.......Ugahhhhhh..... uggaaaughh!!! Uhuhuhaaaaaa!!!!! Uggaugauaaaghuuu!!!!!! Huaa",
      "ts": "2026-04-10T08:14:35.100398"
    },
    {
      "task": "...y, y que... Y qué más queréis saber? Que yo tengo mucho para contaros. Da igual quién sois o dónde estés ahí espiándo",
      "ts": "2026-04-10T08:15:12.354905"
    },
    {
      "task": "--Yeah-- Yeah... yeah? Alright then.Woo hoo.. Yea-ah.... Uh huh...Aww man that's it already?Ughhhh..... Ahhh!!!! Go back",
      "ts": "2026-04-10T08:15:42.195536"
    },
    {
      "task": "(śpiew 00:01:49)",
      "ts": "2026-04-10T08:16:11.260957"
    },
    {
      "task": "Mm-hmm.",
      "ts": "2026-04-10T08:16:35.525072"
    },
    {
      "task": "হ্যালো হ্যালো।",
      "ts": "2026-04-10T08:17:00.453296"
    },
    {
      "task": "--- ...a a-a-...o, o que dizem sobre isso? Obrigada pela atenção e até breve.",
      "ts": "2026-04-10T08:17:27.963827"
    },
    {
      "task": "Yayyy!. . . Wowwwwww... That was fun.... Yeahhhhhh- Oh yeah!! Whoooahh!!!! Let's get loud for the band!, Right? Come on ",
      "ts": "2026-04-10T08:22:41.901010"
    },
    {
      "task": "Ja, ez az. ...az első bújós zene talán nem volt túl jó példa arra- Persze persze... Igen igen....",
      "ts": "2026-04-10T08:23:24.717931"
    },
    {
      "task": ". -- Opa-ahhh-- opa ah...",
      "ts": "2026-04-10T08:23:52.911401"
    }
  ]
}